{
  "doc-6e74d4c894ef8b424ec5c13f46dd0535": {
    "content": "Source: file\nContent:\n李飞飞于1999年从普林斯顿大学本科毕业后赴西藏研究一年藏药；2000年进入加州理工学院；2005年获得加州理工学院博士学位；2005年至2006年担任伊利诺伊大学厄巴纳-香槟分校电机系助理教授；2007年至2009年担任普林斯顿大学计算机科学系助理教授；\n\n[Cognitive Analysis]:\nSummary: 李飞飞是一位著名学者，教育与职业经历横跨普林斯顿、加州理工、伊利诺伊和普林斯顿等多所顶尖高校，深耕于人工智能与计算机科学领域。\nReasoning: 李飞飞的学习与职业路径体现了高度的学术多样性和全球视野，这为她在人工智能和计算机科学领域的发展提供了坚实基础。她的经历说明顶级学者往往需要多学科背景和国际化经验。\nKey Points: 1999年本科毕业于普林斯顿大学，后赴西藏研究藏药一年, 2000年进入加州理工学院，2005年获得博士学位, 2005-2006年在伊利诺伊大学厄巴纳-香槟分校担任助理教授, 2007-2009年在普林斯顿大学计算机科学系担任助理教授\nConcepts: 跨学科研究背景, 学术流动性, 人工智能与计算机科学发展, 国际顶尖高校教育\nEntities: 李飞飞, 普林斯顿大学, 加州理工学院, 伊利诺伊大学厄巴纳-香槟分校, 西藏\nRelations: 李飞飞->本科毕业于->普林斯顿大学, 李飞飞->曾在西藏研究->西藏, 李飞飞->入学->加州理工学院, 李飞飞->获得博士学位->加州理工学院, 李飞飞->任职助理教授->伊利诺伊大学厄巴纳-香槟分校, 李飞飞->任职助理教授->普林斯顿大学\nInferred Relations: 李飞飞->推动/贡献于->人工智能学科发展, 李飞飞->具备高->学术流动性, 李飞飞->拥有->跨学科研究背景, 西藏->可能关联于->人工智能研究, 普林斯顿大学->强学科/研究基地->计算机科学研究\nHypotheses: 李飞飞的西藏研究可能与人工智能在社会科学、地理信息或民族研究中的交叉应用有关。, 其多元的国际顶级高校经历增强了视野广度和学术交流能力，对其学术创新有积极作用。, 李飞飞具有跨文化和跨学科合作经验，这有助于推动人工智能的多领域融合与应用。, 她的学术流动性和多校经历或有助于加强世界范围内人工智能学术网络的交流。\nPotential Links:",
    "file_path": "unknown_source",
    "create_time": 1772947053,
    "update_time": 1772947053,
    "_id": "doc-6e74d4c894ef8b424ec5c13f46dd0535"
  },
  "doc-d0ba32ceb721706b5e036ff927dcb710": {
    "content": "[page_idx:0] 一种轮履变换移动式侦察搜救机器人\n\n总体介绍\n\n本项目研发的轮履变换移动机器人，是一款具有创新性和广泛应用前景的无人陆地侦察机器人。\n\n从研究背景来看，随着国内外对警用及反恐机器人需求的不断增加，我国在该领域虽起步较晚但发展迅速。在轮履复合式机器人中，常见的是轮子和履带为两个零件，需根据地形形状或升降更换，而本项目的轮履变换移动机器人实现了轮/履带整合为一个零件，通过轮子内部机构变换即可实现轮履切换，针对户外复杂场景等应用，具备平地移动速度快、越障能力强、轻巧便携的特点。\n\n该机器人作为国内首创的轮履一体、轮履可切换变形的机器人，采用摩擦驱动模式，轮/履带为独立零件，借助自身弹性及曲柄连杆机构实现轮履切换，同时配备撑杆机构，最大越障高度达15cm，在非结构化环境下地形适应能力和智能自主搜救能力突出，且整体体积小、重量轻、可单人背负、能远程控制，支持多机协作。\n\n目前已有两台样机完成各项越障测试，其系统由车体、通信设备、摄像头等构成，探测距离200m，控制距离覆盖4G网络区，可自主或遥控使用，已在无人巡查中得到应用。\n\n[page_idx:1] 目录\n\n1、绪论………………………………………………………………………………\n  1.1、背景及意义……………………………………………………………………\n  1.2、课题研究现状…………………………………………………………………\n  1.3、建议应用领域…………………………………………………………………\n\n2、成果原理与特点…………………………………………………………………\n  2.1、主要原理………………………………………………………………………\n  2.2、技术特点及优势………………………………………………………………\n\n3、成果转化应用设想……………………………………………………………\n  3.1、成果转化应用总体目标………………………………………………………\n  3.2、成果转化应用研究内容及方案………………………………………………\n\n[page_idx:2] 1、绪论\n\n1.1 背景及意义\n\n    国工控网《警用反恐机器人 的现状与发展趋势》一文中获悉，60年代初，发达国家就开展了警用机器人的研究，研制出多种型号机器人。“9·11”事件以后，各国加强了反恐和排爆机器人的研究，其中，美国、英国、法国、德国、以色列、加拿大、日本等国家处于领先地位。像跋涉机器人、排爆机器人都是非常有特色的，我国在研制警用机器人方面起步较晚，在国家“863”等研究项目的支持下，有了长足的发展，某些技术已经达到国际先进水平。目前国内恐怖形势严峻，涉爆案件增多，严重影响着国家经济建设、安全稳定和人民生命财产的安全。因此，对警用机器人的需求量不断增大。\n\n    我国警用机器人经过近30年的研究取得了丰硕的成果，发挥了重要的作用。目前，国内警用机器人除侦查小型车辆和水下机器人外，按照移动载体主要分为履带式、轮式和轮履复合式三种。按照功能主要分为侦察、排爆燃烬物及危险品、消防、攻击机器人和多功能机器人等。\n\n    其中轮履复合形式，当前一种是轮子和履带为两个零件，因地形需要拆装更换；一种仍是两个零件，回随车携带，通过升降方式更换使用，这两种是当前最常见的；\n\n[page_idx:3] 探测速度：0.5m/s\n\n控制距离：4G 网络覆盖区\n\n安装方式：免安装\n\n供电方式：蓄电池\n\n设备尺寸：0.4m*0.4m*0.3m\n\n使用模式：自主或遥控\n\n应用案例：无人巡查\n\n1.3、建议应用领域\n\n本项目成果向军事侦察、社区监控以及工厂监控等军、民用领域推广，同时向产业化转移，推动机器人产业发展，增加传统产业的附加价值。\n\n本项目成果同时也向抗震救灾，在危险区域寻人、搜救、增援方向推广，协助救援人员获取灾后救援的第一手信息，为生命安全提供希望的通道。\n\n2、成果原理与特点\n\n2.1、主要原理\n\n本项目轮/履变换移动平台是国内首创的轮履一体、轮履可切换变形的机器人，如图1所示。\n\nIV\n\n[page_idx:4] 图1 轮/履变换移动平台\n\n各种侦查搜救现场其共性表现为现场立即变为非常结构化环境，要求机器人平台具有很好的通过性、灵活性，即机器人平台具有很好的越障能力。正是基于这一点，研制一种基于摩擦驱动的侦察搜救机器人——弹性轮/履变换移动平台。\n\n轮/履带变换移动平台是采用摩擦驱动模块式驱动轮/履带，轮/履带为一个独立的零件，并且通过轮/履带自身的弹性以及曲柄连杆机构使轮子在轮/履带之间进行切换，以便完成轮式运行和履带运行的两种运行模式。同时，为了提高机器人快速通行效率以及越障能力，采用履带加摆杆方式，增加摆杆机构，使机器人越障时能够轻松快速越过障碍物，最大越障障高度达到15cm。\n\n当机器人在平坦地面行驶时，轮/履带变换机构早向轮收缩，轮/履带在内圈弹性作用下回弹成轮子并以轮子模式行走，如图2所示；当机器人在非常结构化环境下行驶时，轮/履带被导向轮撑开而形成履带并以履带模式行走，如图3所示；当机器人平台遇到较大障碍物以及台阶时，在履带和摆杆双重作用下越过障碍物，如图4所示。\n\n图2 轮式驱动\n\n[page_idx:5] 图4 跨越障碍\n\n2.2. 技术特点及优势\n\n本项目轮/履变换移动平台在侦察搜救任务中优势突出，在非结构化环境下具有很强的地形适应能力和智能侦查搜救能力。根据特种需求进一步装备拓展，可以实现抵近侦察、索打—体，可进可退的武生设备。具有优越的越障能力，速度快、整体体积小、重量轻、可单人背负使用，远程控制，多机协作完成任务的优势。结合以上优势，我们可以设想如下场景中的应用。\n\n在距离目标位置几公里处，大型运输无人机抵达并投放下若干数量的轮履变换移动机器人，落地后观察并进入伪装潜伏阶段，当前要侦察时，统一激活，各轮履变换移动机器人之间协同配合，共同完成陌生环境下的侦察任务。\n\n当抵达建筑物，需要进行室内秘密侦察时，找准时机，通过崎岖的路面、杂草泥泞的院子，越过斜坡或台阶（如图5所示），通过撬杆加转向末打开门进入，或者通过破洞或缝隙等进入，因为噪声小，体型小的特点不易被察觉，首先原地藏匿监视，然后采取蠕或或者继续前进侦查方案，室内场景通过实时监控摄像头传输，当需要爬\n\n[page_idx:6] 图5 机器人履带模式爬斜坡\n\n或者当抵达建筑物、需要进行人机协作开灭敌人时，轮履变换移动机器人相同的操作，重点是能够实时将敌人隐匿的之处呈现给我方，做到快速发现敌人，准确打击，减少损失的目的。\n\n当面对地震、塌方、火灾等危险情况，本项目的轮履变换移动机器人因具有的越障能力、机动性、远程监控能力等优势对生命财产的抢救提供第一手资料，也在与救援人员、消防员、武警的人机配合中减少进一步损失。\n\n本项目可以考虑防水性能，在涉水方面可以获得进一步潜力开发，充分发挥其优势，为适应全地形侦查搜救而努力。\n\n3、成果转化应用设想\n\n3.1、成果转化应用总体目标\n\n通过本项目研究，所设计的侦察搜救机器人轮/履带变换移动平台在结构化环境下具有快速而灵活的通过性，同时在非结构化环境下的越障越险能力；并将本项目成果向军事侦察、社区监控以及工厂监控等军、民用领域推广，向产业化转移，推动机器人产业发展，同时也向抗震救灾，在狭小危险区域寻人搜救增援方向推广，为拯救更多生命提供援助。\n\n为满足在复杂环境下，例如废墟、台阶、凸台、凹坑、沙地、管\n\n[page_idx:7] 为满足车轮/履带变换模式概念用于社区监控、工厂监控、军事侦察等领域机器人移动平台的设计。增加 4G 数传模块与图传模块，实现监控图像实时传输与保存，根据实时图像远程实时控制移动平台完成监控/侦察任务，并且由于使用小型优质电机，整体体积小重量轻，满足随身携带、满足侦察速度等多项侦察要求。\n\n3.2、成果转化应用研究内容\n\n本项目的侦查搜救机器人—轮/履带变换移动平台包括 MCU 中央处理单元、电机驱动部分、图像传输模块、远程控制模块、电池模块等，各单元模块共同组成了如图 6 所示的轮/履带变换移动平台的系统架构。\n\n该系统的成果转化应用的研究内容包括以下三点。\n\n1、轮/履带变换移动平台如何可靠的快速驱动\n\n侦查搜救机器人的高性能机动性是执行侦查搜救任务基本要求，出于对战士、受灾群众的生命负责的态度，所研制设备必须具有高性能机动性以及高的可靠性。高性能机动性对电机性能、运动方式、续航能力有很高要求，所以在硬件方面的搭建以获得高性能机动性是成果转化到实际应用的关键一步。\n\n2、轮/履带变换移动平台如何可靠的实现远程操控、多机协作\n\n[page_idx:8] 有效测试以验证设备性能是获得整机性能最直观的方法，本项目的轮/履带交换\n移动平台将研究各项测试方案，以证明其成果转化的运行可靠性，尤其在越障\n能力的考核上设计尽可能多的方案，如废墟、台阶、凸台、凹坑、沙地、管\n道、泥泞环境障碍等非结构化环境下的通过性。\n\n环境\n——————————————————————————————————————————————\n|    左轮电机    |    左轮电机    |    右轮电机    |    右轮电机    |    摄像头设备    |\n|    左轮驱动    |    左轮驱动    |    右轮驱动    |    右轮驱动    |                 |\n|    左履带带    |    左履带带    |    右履带带    |    右履带带    |                 |\n|    左履带驱动  |    左履带驱动  |    右履带驱动  |    右履带驱动  |                 |\n|    MC U+电源   |                |    右履带驱动  |                |                 |\n——————————————————————————————————————————————\n|    操作手驱动  |    DTU         |    天线        |    天线        |\n|    操作手电机  |                |                |                |\n——————————————————————————————————————————————\n|    服务器平台端设备    |\n|    无线传输            |\n|    远程控制端          |\n————————————————————————————————————————",
    "file_path": "产品说明书.pdf",
    "create_time": 1772954363,
    "update_time": 1772954363,
    "_id": "doc-d0ba32ceb721706b5e036ff927dcb710"
  }
}