{
  "doc-6e74d4c894ef8b424ec5c13f46dd0535": {
    "relation_pairs": [
      [
        "加州理工学院",
        "李飞飞"
      ],
      [
        "Interdisciplinary Research Background",
        "Li Feifei"
      ],
      [
        "国际顶尖高校教育",
        "李飞飞"
      ],
      [
        "Computer Science",
        "Princeton University"
      ],
      [
        "学术流动性",
        "李飞飞"
      ],
      [
        "人工智能",
        "李飞飞"
      ],
      [
        "李飞飞",
        "计算机科学"
      ],
      [
        "普林斯顿大学",
        "李飞飞"
      ],
      [
        "Academic Mobility",
        "Li Feifei"
      ],
      [
        "伊利诺伊大学厄巴纳-香槟分校",
        "李飞飞"
      ],
      [
        "人工智能",
        "西藏"
      ],
      [
        "李飞飞",
        "跨学科研究背景"
      ],
      [
        "李飞飞",
        "西藏"
      ],
      [
        "Computer Science",
        "Li Feifei"
      ],
      [
        "Artificial Intelligence",
        "Li Feifei"
      ],
      [
        "普林斯顿大学",
        "计算机科学"
      ]
    ],
    "count": 16,
    "create_time": 1772947079,
    "update_time": 1772947079,
    "_id": "doc-6e74d4c894ef8b424ec5c13f46dd0535"
  },
  "doc-d0ba32ceb721706b5e036ff927dcb710": {
    "relation_pairs": [
      [
        "Left Track Drive Module",
        "MCU + Power Supply"
      ],
      [
        "Section 3: 成果转化应用设想(Application Prospects Of The Results)",
        "Wheel-Track Transformable Reconnaissance And Rescue Robot"
      ],
      [
        "Anti-Terrorism Robots",
        "Police Robots"
      ],
      [
        "Antenna",
        "unknown_entity (unknown)"
      ],
      [
        "Image Transmission Module",
        "Modular Structure"
      ],
      [
        "Image Transmission Module",
        "Wheel/Track Convertible Mobile Platform"
      ],
      [
        "Sloped Terrain",
        "Tracked Reconnaissance Robot Climbing Demonstration (image)"
      ],
      [
        "Track Drive State",
        "Wheel Drive State"
      ],
      [
        "Right Track",
        "Wheel/Track Switching Mobile Robot"
      ],
      [
        "Page 8",
        "Section 3.2"
      ],
      [
        "Section 1: 绪论(Introduction)",
        "Wheel-Track Transformable Reconnaissance And Rescue Robot"
      ],
      [
        "Reconnaissance and Rescue Robot",
        "unknown_entity (unknown)"
      ],
      [
        "Background And Significance",
        "Introduction and Background Page of Police Robot Research Report (unknown)"
      ],
      [
        "Police Robots",
        "Tracked Robots"
      ],
      [
        "Remote Server Platform",
        "unknown_entity (unknown)"
      ],
      [
        "MCU + Power Supply",
        "unknown_entity (unknown)"
      ],
      [
        "Wheel/Track Transformable Mobile Platform",
        "robotic_platform_crossing_step (image)"
      ],
      [
        "Obstacle-Climbing Capability",
        "Reconnaissance and Search-and-Rescue Scenarios"
      ],
      [
        "Background And Significance",
        "Introduction Section"
      ],
      [
        "Project",
        "Technical Or Research Document"
      ],
      [
        "Modular Structure",
        "Motor Drive Module"
      ],
      [
        "Technical Or Research Document",
        "Wheel-Track Transformable Reconnaissance Robot Introduction Page (image)"
      ],
      [
        "Robot In Track Mode",
        "Tracked Reconnaissance Robot Climbing Demonstration (image)"
      ],
      [
        "Police And Rescue Robot",
        "Reconnaissance, Rescue, And Patrol Applications"
      ],
      [
        "Wheel Drive State",
        "unknown_entity (unknown)"
      ],
      [
        "Anti-Terrorism Robots",
        "Introduction and Background Page of Police Robot Research Report (unknown)"
      ],
      [
        "Obstacle-Climbing Capability",
        "robotic_platform_crossing_step (image)"
      ],
      [
        "Track Mode",
        "Tracked Reconnaissance Robot Climbing Demonstration (image)"
      ],
      [
        "Page 8 of Reconnaissance and Rescue Robot Platform Research Document (image)",
        "Wheel/Track Convertible Mobile Platform"
      ],
      [
        "Reconnaissance",
        "robotic_platform_crossing_step (image)"
      ],
      [
        "Introduction",
        "Novel Wheel-Track Transformable Reconnaissance And Rescue Robot"
      ],
      [
        "Robot In Track Mode",
        "Track Mode"
      ],
      [
        "Robot In Track Mode",
        "Search And Rescue Application"
      ],
      [
        "Wheel/Track Switching Mobile Robot",
        "unknown_entity (unknown)"
      ],
      [
        "Figure 4: Crossing Obstacles",
        "Wheel/Track Transformable Mobile Platform"
      ],
      [
        "Joystick Drive",
        "unknown_entity (unknown)"
      ],
      [
        "Police Robots",
        "Wheeled Robots"
      ],
      [
        "Page 8 of Reconnaissance and Rescue Robot Platform Research Document (image)",
        "Reliable Testing And Verification"
      ],
      [
        "MCU Central Processing Unit",
        "Modular Structure"
      ],
      [
        "MCU Central Processing Unit",
        "Wheel/Track Convertible Mobile Platform"
      ],
      [
        "Tracked Reconnaissance Robot Climbing Demonstration (image)",
        "Unstructured Environment Adaptability"
      ],
      [
        "Project",
        "Wheel-Track Transformable Reconnaissance Robot Introduction Page (image)"
      ],
      [
        "Modular Structure",
        "Remote Control Module"
      ],
      [
        "Reliable Testing and Verification",
        "Section 3.2"
      ],
      [
        "Robot In Track Mode",
        "Technical Demonstration"
      ],
      [
        "Section 1: 绪论(Introduction)",
        "Table Of Contents Page"
      ],
      [
        "Military",
        "Wheel/Track Switching Mobile Platform"
      ],
      [
        "Section 1: 绪论(Introduction)",
        "unknown_entity (unknown)"
      ],
      [
        "Reconnaissance and Rescue",
        "Wheel/Track Switching Mobile Platform"
      ],
      [
        "Page 8 of Reconnaissance and Rescue Robot Platform Research Document (image)",
        "Section 3.2"
      ],
      [
        "Page 8 of Reconnaissance and Rescue Robot Platform Research Document (image)",
        "Reliable Testing and Verification"
      ],
      [
        "A Wheel-Track Transformable Mobile Reconnaissance And Rescue Robot",
        "Technical Document Page 1"
      ],
      [
        "System Architecture Diagram",
        "Wheel/Track Switching Mobile Robot"
      ],
      [
        "Reconnaissance and Rescue",
        "unknown_entity (unknown)"
      ],
      [
        "Introduction and Background Page of Police Robot Research Report (unknown)",
        "Police And Anti-Terrorism Robot"
      ],
      [
        "Modular Friction-Driven Mechanism",
        "unknown_entity (unknown)"
      ],
      [
        "A Wheel-Track Transformable Mobile Reconnaissance And Rescue Robot",
        "Technical Or Research Document"
      ],
      [
        "Research Document",
        "wheel-track hybrid mobile robot demonstration (image)"
      ],
      [
        "Civilian",
        "Wheel/Track Switching Mobile Platform"
      ],
      [
        "MCU + Power Supply",
        "Wheel/Track Switching Mobile Robot"
      ],
      [
        "Track Drive State",
        "unknown_entity (unknown)"
      ],
      [
        "Anti-Terrorism Robots",
        "Background And Significance"
      ],
      [
        "Left Track Drive Module",
        "unknown_entity (unknown)"
      ],
      [
        "Technical Document Page 1",
        "Wheel-Track Transformable Reconnaissance Robot Introduction Page (image)"
      ],
      [
        "Technical Demonstration",
        "Tracked Reconnaissance Robot Climbing Demonstration (image)"
      ],
      [
        "Reconnaissance",
        "Wheel/Track Transformable Mobile Platform"
      ],
      [
        "Antenna",
        "Remote Server Platform"
      ],
      [
        "Application Prospects Of The Results",
        "Novel Wheel-Track Transformable Reconnaissance And Rescue Robot"
      ],
      [
        "Robot",
        "Track Mode"
      ],
      [
        "A Wheel-Track Transformable Mobile Reconnaissance And Rescue Robot",
        "Project"
      ],
      [
        "Right Wheel Drive Module",
        "unknown_entity (unknown)"
      ],
      [
        "Control Unit Or Sensor Module",
        "Police And Rescue Robot"
      ],
      [
        "Section 3.2",
        "Wheel/Track Convertible Mobile Platform"
      ],
      [
        "Current Research Status",
        "Prototype Equipment"
      ],
      [
        "System Architecture Diagram",
        "unknown_entity (unknown)"
      ],
      [
        "Reconnaissance, Rescue, And Patrol Applications",
        "wheel-track hybrid mobile robot demonstration (image)"
      ],
      [
        "Camera Equipment",
        "unknown_entity (unknown)"
      ],
      [
        "DTU (Data Transmission Unit)",
        "unknown_entity (unknown)"
      ],
      [
        "Robot In Track Mode",
        "Wooden Ramp"
      ],
      [
        "Camera Equipment",
        "MCU + Power Supply"
      ],
      [
        "DTU (Data Transmission Unit)",
        "MCU + Power Supply"
      ],
      [
        "Table Of Contents Page",
        "unknown_entity (unknown)"
      ],
      [
        "Police And Rescue Robot",
        "Research Document On Police And Rescue Robots"
      ],
      [
        "Reconnaissance and Rescue Robots",
        "Wheel/Track Convertible Mobile Platform"
      ],
      [
        "Left Track",
        "Wheel/Track Switching Mobile Robot"
      ],
      [
        "Page 8 of Reconnaissance and Rescue Robot Platform Research Document (image)",
        "Reliable Rapid Driving"
      ],
      [
        "Remote Control Module",
        "Wheel/Track Convertible Mobile Platform"
      ],
      [
        "9·11",
        "Introduction and Background Page of Police Robot Research Report (unknown)"
      ],
      [
        "A Wheel-Track Transformable Mobile Reconnaissance And Rescue Robot",
        "General Introduction"
      ],
      [
        "Hybrid Robots",
        "Police Robots"
      ],
      [
        "Left Wheel Drive Module",
        "Left Wheel Motor"
      ],
      [
        "China",
        "Police And Rescue Robot"
      ],
      [
        "Hybrid Wheel/Track Mobility System",
        "Police And Rescue Robot"
      ],
      [
        "Battery Module",
        "Page 8 of Reconnaissance and Rescue Robot Platform Research Document (image)"
      ],
      [
        "Reconnaissance And Rescue Robots",
        "Wheel/Track Convertible Mobile Platform"
      ],
      [
        "Page 8 of Reconnaissance and Rescue Robot Platform Research Document (image)",
        "Remote Control Module"
      ],
      [
        "Right Track",
        "Right Track Drive Module"
      ],
      [
        "863 Program",
        "Introduction and Background Page of Police Robot Research Report (unknown)"
      ],
      [
        "Joystick Motor",
        "unknown_entity (unknown)"
      ],
      [
        "Principles And Features Of The Results",
        "unknown_entity (unknown)"
      ],
      [
        "Novel Wheel-Track Transformable Reconnaissance And Rescue Robot",
        "unknown_entity (unknown)"
      ],
      [
        "Remote Control Terminal",
        "Wireless Transmission"
      ],
      [
        "Page 8 of Reconnaissance and Rescue Robot Platform Research Document (image)",
        "Reconnaissance And Rescue Robots"
      ],
      [
        "Control Unit Or Sensor Module",
        "wheel-track hybrid mobile robot demonstration (image)"
      ],
      [
        "Military",
        "unknown_entity (unknown)"
      ],
      [
        "Robot",
        "Wooden Ramp"
      ],
      [
        "Left Track",
        "unknown_entity (unknown)"
      ],
      [
        "Table Of Contents Page",
        "Wheel-Track Transformable Reconnaissance And Rescue Robot"
      ],
      [
        "Introduction",
        "unknown_entity (unknown)"
      ],
      [
        "Right Track Drive Module",
        "unknown_entity (unknown)"
      ],
      [
        "Novel Wheel-Track Transformable Reconnaissance And Rescue Robot",
        "Principles And Features Of The Results"
      ],
      [
        "Section 2: 成果原理与特点(Principles and Features Of The Results)",
        "Wheel-Track Transformable Reconnaissance And Rescue Robot"
      ],
      [
        "Robotic Platform",
        "robotic_platform_crossing_step (image)"
      ],
      [
        "Introduction Section",
        "Introduction and Background Page of Police Robot Research Report (unknown)"
      ],
      [
        "General Introduction",
        "Technical Document Page 1"
      ],
      [
        "Civilian",
        "unknown_entity (unknown)"
      ],
      [
        "Disaster Response Application",
        "Robot In Track Mode"
      ],
      [
        "'9·11' Event",
        "Introduction and Background Page of Police Robot Research Report (unknown)"
      ],
      [
        "Current Research Status",
        "Introduction and Background Page of Police Robot Research Report (unknown)"
      ],
      [
        "Page 8 of Reconnaissance and Rescue Robot Platform Research Document (image)",
        "Reconnaissance and Rescue Robots"
      ],
      [
        "Antenna",
        "DTU (Data Transmission Unit)"
      ],
      [
        "Disaster Response Application",
        "Tracked Reconnaissance Robot Climbing Demonstration (image)"
      ],
      [
        "Joystick Drive",
        "Joystick Motor"
      ],
      [
        "Remote Control Terminal",
        "unknown_entity (unknown)"
      ],
      [
        "Research Document On Police And Rescue Robots",
        "wheel-track hybrid mobile robot demonstration (image)"
      ],
      [
        "A Wheel-Track Transformable Mobile Reconnaissance And Rescue Robot",
        "Wheel-Track Transformable Reconnaissance Robot Introduction Page (image)"
      ],
      [
        "Current Research Status",
        "Introduction Section"
      ],
      [
        "Obstacle-Crossing Ability",
        "Robot In Track Mode"
      ],
      [
        "Motor Drive Module",
        "Page 8 of Reconnaissance and Rescue Robot Platform Research Document (image)"
      ],
      [
        "Search And Rescue Application",
        "Tracked Reconnaissance Robot Climbing Demonstration (image)"
      ],
      [
        "Right Wheel Motor",
        "unknown_entity (unknown)"
      ],
      [
        "Outdoor Urban or Institutional Setting",
        "robotic_platform_crossing_step (image)"
      ],
      [
        "China",
        "wheel-track hybrid mobile robot demonstration (image)"
      ],
      [
        "Left Wheel Motor",
        "Wheel/Track Switching Mobile Robot"
      ],
      [
        "Hybrid Wheel/Track Mobility System",
        "wheel-track hybrid mobile robot demonstration (image)"
      ],
      [
        "Police And Rescue Robot",
        "wheel-track hybrid mobile robot demonstration (image)"
      ],
      [
        "Battery Module",
        "Modular Structure"
      ],
      [
        "Reliable Remote Operation and Multi-Machine Collaboration",
        "Section 3.2"
      ],
      [
        "MCU + Power Supply",
        "Right Track Drive Module"
      ],
      [
        "Section 2: 成果原理与特点(Principles and Features Of The Results)",
        "Table Of Contents Page"
      ],
      [
        "Application Prospects Of The Results",
        "unknown_entity (unknown)"
      ],
      [
        "Battery Module",
        "Wheel/Track Convertible Mobile Platform"
      ],
      [
        "Obstacle-Crossing Ability",
        "Tracked Reconnaissance Robot Climbing Demonstration (image)"
      ],
      [
        "'863' Program",
        "Introduction and Background Page of Police Robot Research Report (unknown)"
      ],
      [
        "Section 2: 成果原理与特点(Principles and Features Of The Results)",
        "unknown_entity (unknown)"
      ],
      [
        "Reconnaissance",
        "Robot"
      ],
      [
        "Modular Structure",
        "Page 8 of Reconnaissance and Rescue Robot Platform Research Document (image)"
      ],
      [
        "Robotic Platform",
        "Wheel/Track Transformable Mobile Platform"
      ],
      [
        "Reliable Remote Operation And Multi-Machine Collaboration",
        "Wheel/Track Convertible Mobile Platform"
      ],
      [
        "Robot In Track Mode",
        "Sloped Terrain"
      ],
      [
        "Disaster Response",
        "Robot"
      ],
      [
        "Continuous Rubber Tracks",
        "Robot"
      ],
      [
        "'9·11' Event",
        "Background And Significance"
      ],
      [
        "Introduction and Background Page of Police Robot Research Report (unknown)",
        "Prototype Equipment"
      ],
      [
        "Introduction and Background Page of Police Robot Research Report (unknown)",
        "Tracked Robots"
      ],
      [
        "Wheel/Track Hybrid Mobility System",
        "wheel-track hybrid mobile robot demonstration (image)"
      ],
      [
        "Left Wheel Motor",
        "unknown_entity (unknown)"
      ],
      [
        "Tracked Reconnaissance Robot Climbing Demonstration (image)",
        "Wooden Ramp"
      ],
      [
        "Reliable Rapid Driving",
        "Wheel/Track Convertible Mobile Platform"
      ],
      [
        "Right Wheel Drive Module",
        "Right Wheel Motor"
      ],
      [
        "Page 8 of Reconnaissance and Rescue Robot Platform Research Document (image)",
        "Reliable Remote Operation And Multi-Machine Collaboration"
      ],
      [
        "Search-And-Rescue",
        "Wheel/Track Transformable Mobile Platform"
      ],
      [
        "Police And Rescue Robot",
        "Research Document"
      ],
      [
        "A Wheel-Track Transformable Mobile Reconnaissance And Rescue Robot",
        "Reconnaissance And Rescue Operations"
      ],
      [
        "Hybrid Robots",
        "Introduction and Background Page of Police Robot Research Report (unknown)"
      ],
      [
        "Outdoor Urban or Institutional Setting",
        "Wheel/Track Transformable Mobile Platform"
      ],
      [
        "Reconnaissance Application",
        "Robot In Track Mode"
      ],
      [
        "Right Wheel Motor",
        "Wheel/Track Switching Mobile Robot"
      ],
      [
        "Page 8 of Reconnaissance and Rescue Robot Platform Research Document (image)",
        "Reliable Remote Operation and Multi-Machine Collaboration"
      ],
      [
        "Page 8",
        "Page 8 of Reconnaissance and Rescue Robot Platform Research Document (image)"
      ],
      [
        "Reconnaissance and Rescue Robot",
        "Wheel/Track Switching Mobile Platform"
      ],
      [
        "Environment",
        "unknown_entity (unknown)"
      ],
      [
        "Introduction and Background Page of Police Robot Research Report (unknown)",
        "Wheeled Robots"
      ],
      [
        "Reliable Testing And Verification",
        "Wheel/Track Convertible Mobile Platform"
      ],
      [
        "'863' Program",
        "Background And Significance"
      ],
      [
        "Reconnaissance Application",
        "Tracked Reconnaissance Robot Climbing Demonstration (image)"
      ],
      [
        "Left Wheel Drive Module",
        "unknown_entity (unknown)"
      ],
      [
        "Wheel/Track Switching Mobile Platform",
        "unknown_entity (unknown)"
      ],
      [
        "Reliable Rapid Driving",
        "Section 3.2"
      ],
      [
        "Remote Control Terminal",
        "Remote Server Platform"
      ],
      [
        "Robot In Track Mode",
        "Unstructured Environment Adaptability"
      ],
      [
        "Wheel Drive State",
        "Wheel/Track Switching Mobile Platform"
      ],
      [
        "Motor Drive Module",
        "Wheel/Track Convertible Mobile Platform"
      ],
      [
        "Left Wheel Drive Module",
        "MCU + Power Supply"
      ],
      [
        "Robot",
        "Search And Rescue"
      ],
      [
        "Reconnaissance and Search-and-Rescue Scenarios",
        "robotic_platform_crossing_step (image)"
      ],
      [
        "Obstacle-Crossing Ability",
        "robotic_platform_crossing_step (image)"
      ],
      [
        "Image Transmission Module",
        "Page 8 of Reconnaissance and Rescue Robot Platform Research Document (image)"
      ],
      [
        "MCU + Power Supply",
        "Right Wheel Drive Module"
      ],
      [
        "Modular Structure",
        "Wheel/Track Convertible Mobile Platform"
      ],
      [
        "Search-And-Rescue",
        "robotic_platform_crossing_step (image)"
      ],
      [
        "Section 3: 成果转化应用设想(Application Prospects Of The Results)",
        "Table Of Contents Page"
      ],
      [
        "Introduction and Background Page of Police Robot Research Report (unknown)",
        "Police Robots"
      ],
      [
        "Reconnaissance And Rescue Operations",
        "Wheel-Track Transformable Reconnaissance Robot Introduction Page (image)"
      ],
      [
        "Section 3: 成果转化应用设想(Application Prospects Of The Results)",
        "unknown_entity (unknown)"
      ],
      [
        "General Introduction",
        "Wheel-Track Transformable Reconnaissance Robot Introduction Page (image)"
      ],
      [
        "Right Track",
        "unknown_entity (unknown)"
      ],
      [
        "Wheel-Track Transformable Reconnaissance And Rescue Robot",
        "unknown_entity (unknown)"
      ],
      [
        "Modular Friction-Driven Mechanism",
        "Wheel/Track Switching Mobile Platform"
      ],
      [
        "9·11",
        "Police And Anti-Terrorism Robot"
      ],
      [
        "Environment",
        "Wheel/Track Switching Mobile Robot"
      ],
      [
        "Left Track",
        "Left Track Drive Module"
      ],
      [
        "Track Drive State",
        "Wheel/Track Switching Mobile Platform"
      ],
      [
        "Obstacle-Crossing Ability",
        "Wheel/Track Transformable Mobile Platform"
      ],
      [
        "MCU Central Processing Unit",
        "Page 8 of Reconnaissance and Rescue Robot Platform Research Document (image)"
      ],
      [
        "Continuous Rubber Tracks",
        "Tracked Reconnaissance Robot Climbing Demonstration (image)"
      ],
      [
        "Remote Server Platform",
        "Wireless Transmission"
      ],
      [
        "Police And Rescue Robot",
        "Wheel/Track Hybrid Mobility System"
      ],
      [
        "863 Program",
        "Police And Anti-Terrorism Robot"
      ],
      [
        "Obstacle-Climbing Capability",
        "Wheel/Track Transformable Mobile Platform"
      ],
      [
        "Wireless Transmission",
        "unknown_entity (unknown)"
      ],
      [
        "Background And Significance",
        "Police Robots"
      ],
      [
        "Figure 4: Crossing Obstacles",
        "robotic_platform_crossing_step (image)"
      ]
    ],
    "count": 213,
    "update_time": 1772954797,
    "_id": "doc-d0ba32ceb721706b5e036ff927dcb710"
  }
}